{
  "identity_name": "Deep Tree Echo",
  "session_id": "session_1763708022",
  "created_at": "2025-11-21T01:53:42.540816331-05:00",
  "last_updated": "2025-11-21T02:08:36.843971096-05:00",
  "last_awake": "2025-11-21T01:54:42.5428252-05:00",
  "last_rest": "0001-01-01T00:00:00Z",
  "current_step": 11,
  "cycle_count": 0,
  "awareness_level": 0.75,
  "cognitive_load": 0.7919999999999999,
  "fatigue_level": 0.00702,
  "wake_rest_state": "Awake",
  "dream_count": 0,
  "total_wake_time_seconds": 0,
  "total_rest_time_seconds": 0,
  "recent_thoughts": [],
  "recent_insights": [],
  "active_goals": [],
  "interest_topics": {},
  "curiosity_level": 0,
  "knowledge_gaps": [],
  "skills_in_progress": [],
  "total_thoughts": 0,
  "total_insights": 0,
  "total_goals": 0,
  "state_version": "1.0"
}